liora/__init__.py
liora/agent.py
liora/benchmarking.py
liora/environment.py
liora/interpretation.py
liora/mixin.py
liora/model.py
liora/module.py
liora/ode_functions.py
liora/utils.py
liora/distributions/__init__.py
liora/distributions/utils.py
liora/distributions/EuclideanNormal/__init__.py
liora/distributions/EuclideanNormal/arguments.py
liora/distributions/EuclideanNormal/distribution.py
liora/distributions/EuclideanNormal/layers.py
liora/distributions/EuclideanNormal/prior.py
liora/distributions/HWNormal/__init__.py
liora/distributions/HWNormal/arguments.py
liora/distributions/HWNormal/distribution.py
liora/distributions/HWNormal/layers.py
liora/distributions/HWNormal/prior.py
liora/distributions/LearnablePGMNormal/__init__.py
liora/distributions/LearnablePGMNormal/arguments.py
liora/distributions/LearnablePGMNormal/distribution.py
liora/distributions/LearnablePGMNormal/layers.py
liora/distributions/LearnablePGMNormal/prior.py
liora/distributions/PGMNormal/__init__.py
liora/distributions/PGMNormal/arguments.py
liora/distributions/PGMNormal/distribution.py
liora/distributions/PGMNormal/layers.py
liora/distributions/PGMNormal/prior.py
liora/distributions/PoincareNormal/__init__.py
liora/distributions/PoincareNormal/arguments.py
liora/distributions/PoincareNormal/ars.py
liora/distributions/PoincareNormal/distribution.py
liora/distributions/PoincareNormal/hyperbolic_radius.py
liora/distributions/PoincareNormal/hyperbolic_uniform.py
liora/distributions/PoincareNormal/layers.py
liora/distributions/PoincareNormal/prior.py
liora/unified_models/__init__.py
liora/unified_models/base_model.py
liora/unified_models/cellblast_model.py
liora/unified_models/clear_model.py
liora/unified_models/gmvae_model.py
liora/unified_models/scalex_model.py
liora/unified_models/scdac_model.py
liora/unified_models/scdeepcluster_model.py
liora/unified_models/scdhmap_model.py
liora/unified_models/scdiffusion_model.py
liora/unified_models/scgcc_model.py
liora/unified_models/scgnn_model.py
liora-0.4.3.dist-info/licenses/LICENSE
liora-0.4.3.dist-info/METADATA
liora-0.4.3.dist-info/WHEEL
liora-0.4.3.dist-info/top_level.txt
liora-0.4.3.dist-info/RECORD
