Metadata-Version: 2.4
Name: liora
Version: 0.4.3
Summary: Liora: Lorentz Interpretable ODE-Regularized Attention-based VAE
Author-email: Zeyu Fu <fuzeyu99@126.com>
Maintainer-email: Zeyu Fu <fuzeyu99@126.com>
License: MIT License
Project-URL: Homepage, https://github.com/PeterPonyu/Liora
Project-URL: Repository, https://github.com/PeterPonyu/Liora
Project-URL: Issues, https://github.com/PeterPonyu/Liora/issues
Project-URL: Documentation, https://github.com/PeterPonyu/Liora#readme
Keywords: single-cell,rna-seq,scRNA-seq,vae,variational-autoencoder,neural-ode,ode,manifold,lorentz,hyperbolic,transformer,trajectory-inference,bioinformatics
Classifier: Development Status :: 3 - Alpha
Classifier: Intended Audience :: Science/Research
Classifier: Programming Language :: Python :: 3
Classifier: Programming Language :: Python :: 3.9
Classifier: Programming Language :: Python :: 3.10
Classifier: Programming Language :: Python :: 3.11
Classifier: Programming Language :: Python :: 3.12
Classifier: Topic :: Scientific/Engineering :: Bio-Informatics
Classifier: Topic :: Scientific/Engineering :: Artificial Intelligence
Classifier: Topic :: Scientific/Engineering :: Medical Science Apps.
Requires-Python: >=3.9
License-File: LICENSE
Requires-Dist: torch>=2.1
Requires-Dist: torchdiffeq>=0.2.3
Requires-Dist: numpy>=1.23
Requires-Dist: scipy>=1.9
Requires-Dist: scikit-learn>=1.1
Requires-Dist: anndata>=0.9
Requires-Dist: tqdm>=4.65
Provides-Extra: test
Requires-Dist: pytest>=7.0; extra == "test"
Requires-Dist: pytest-cov>=4.0; extra == "test"
Provides-Extra: dev
Requires-Dist: pytest>=7.0; extra == "dev"
Requires-Dist: pytest-cov>=4.0; extra == "dev"
Requires-Dist: black>=23.0; extra == "dev"
Requires-Dist: isort>=5.12; extra == "dev"
Requires-Dist: flake8>=6.0; extra == "dev"
Dynamic: license-file
